pgcolorbar/__init__.py
pgcolorbar/bindings.py
pgcolorbar/colorlegend.py
pgcolorbar/demo.py
pgcolorbar/misc.py
pgcolorbar/version.txt
pgcolorbar-1.1.3.dist-info/LICENSE
pgcolorbar-1.1.3.dist-info/METADATA
pgcolorbar-1.1.3.dist-info/WHEEL
pgcolorbar-1.1.3.dist-info/entry_points.txt
pgcolorbar-1.1.3.dist-info/top_level.txt
pgcolorbar-1.1.3.dist-info/RECORD
